[{"token_index": 0, "start_ms": 100.0, "end_ms": 562.5}, {"token_index": 2, "start_ms": 612.5, "end_ms": 887.5}, {"token_index": 3, "start_ms": 887.5, "end_ms": 1337.5}, {"token_index": 5, "start_ms": 1437.5, "end_ms": 1500.0}, {"token_index": 6, "start_ms": 1525.0, "end_ms": 1762.5}, {"token_index": 7, "start_ms": 1762.5, "end_ms": 1962.5}, {"token_index": 8, "start_ms": 1962.5, "end_ms": 2237.5}, {"token_index": 10, "start_ms": 2337.5, "end_ms": 2587.5}, {"token_index": 11, "start_ms": 2625.0, "end_ms": 3137.5}, {"token_index": 13, "start_ms": 3162.5, "end_ms": 3312.5}, {"token_index": 14, "start_ms": 3325.0, "end_ms": 3500.0}, {"token_index": 15, "start_ms": 3512.5, "end_ms": 3887.5}]