[{"token_index": 1, "start_ms": 100.0, "end_ms": 225.0}, {"token_index": 2, "start_ms": 225.0, "end_ms": 687.5}, {"token_index": 4, "start_ms": 750.0, "end_ms": 1225.0}, {"token_index": 7, "start_ms": 1312.5, "end_ms": 1862.5}, {"token_index": 8, "start_ms": 1887.5, "end_ms": 2150.0}, {"token_index": 9, "start_ms": 2162.5, "end_ms": 2700.0}, {"token_index": 10, "start_ms": 2712.5, "end_ms": 2787.5}, {"token_index": 11, "start_ms": 2787.5, "end_ms": 3200.0}, {"token_index": 12, "start_ms": 3200.0, "end_ms": 3650.0}]